py_type_converter/__init__.py
py_type_converter/converter.py
py_type_converter-0.0.5.dist-info/METADATA
py_type_converter-0.0.5.dist-info/WHEEL
py_type_converter-0.0.5.dist-info/top_level.txt
py_type_converter-0.0.5.dist-info/RECORD
