Metadata-Version: 2.1
Name: py-type-converter
Version: 0.0.5
Summary: Python type converter.
Author: Veysel AKSIN (lainnyone)
Author-email: <veyselaksn@gmail.com>
License: UNKNOWN
Keywords: python,converter,convert,tuple,list,dictionary
Platform: UNKNOWN
Classifier: Development Status :: 1 - Planning
Classifier: Intended Audience :: Developers
Classifier: Programming Language :: Python :: 3
Classifier: Operating System :: Unix
Classifier: Operating System :: MacOS :: MacOS X
Classifier: Operating System :: Microsoft :: Windows
